pitv/__init__.py
pitv/pitv.py
pitv-0.0.11.dist-info/LICENSE.txt
pitv-0.0.11.dist-info/METADATA
pitv-0.0.11.dist-info/WHEEL
pitv-0.0.11.dist-info/entry_points.txt
pitv-0.0.11.dist-info/RECORD
